{
  "_class": "shapePath",
  "booleanOperation": 1,
  "do_objectID": "74A097BD-FB01-4AA2-AE0A-DD12AF014CCC",
  "edited": true,
  "exportOptions": {
    "_class": "exportOptions",
    "exportFormats": [
    ],
    "includedLayerIds": [
    ],
    "layerOptions": 0,
    "shouldTrim": false
  },
  "frame": {
    "_class": "rect",
    "constrainProportions": false,
    "height": 5.705686664006795,
    "width": 2.850003397464752,
    "x": 4.987505945563316,
    "y": 8.558529996010193
  },
  "isClosed": true,
  "isFlippedHorizontal": false,
  "isFlippedVertical": false,
  "isLocked": false,
  "isVisible": true,
  "layerListExpandedType": 0,
  "name": "Path",
  "nameIsFixed": false,
  "path": {
    "_class": "path",
    "isClosed": true,
    "pointRadiusBehaviour": 0,
    "points": [
      {
        "_class": "curvePoint",
        "cornerRadius": 0,
        "curveFrom": "{1, 0.970703125}",
        "curveMode": 4,
        "curveTo": "{1, 0.9375}",
        "hasCurveFrom": true,
        "hasCurveTo": false,
        "point": "{1, 0.9375}"
      },
      {
        "_class": "curvePoint",
        "cornerRadius": 0,
        "curveFrom": "{0.875, 1}",
        "curveMode": 4,
        "curveTo": "{0.94140625, 1}",
        "hasCurveFrom": false,
        "hasCurveTo": true,
        "point": "{0.875, 1}"
      },
      {
        "_class": "curvePoint",
        "cornerRadius": 0,
        "curveFrom": "{0.05859375, 1}",
        "curveMode": 4,
        "curveTo": "{0.125, 1}",
        "hasCurveFrom": true,
        "hasCurveTo": false,
        "point": "{0.125, 1}"
      },
      {
        "_class": "curvePoint",
        "cornerRadius": 0,
        "curveFrom": "{0, 0.91015625}",
        "curveMode": 2,
        "curveTo": "{0, 0.970703125}",
        "hasCurveFrom": true,
        "hasCurveTo": true,
        "point": "{0, 0.9375}"
      },
      {
        "_class": "curvePoint",
        "cornerRadius": 0,
        "curveFrom": "{0.109375, 0.4296875}",
        "curveMode": 4,
        "curveTo": "{0.2421875, 0.525390625}",
        "hasCurveFrom": true,
        "hasCurveTo": true,
        "point": "{0.2734375, 0.47265625}"
      },
      {
        "_class": "curvePoint",
        "cornerRadius": 0,
        "curveFrom": "{0, 0.111328125}",
        "curveMode": 3,
        "curveTo": "{0, 0.34375}",
        "hasCurveFrom": true,
        "hasCurveTo": true,
        "point": "{0, 0.25}"
      },
      {
        "_class": "curvePoint",
        "cornerRadius": 0,
        "curveFrom": "{0.77734375, 0}",
        "curveMode": 2,
        "curveTo": "{0.22265625, 0}",
        "hasCurveFrom": true,
        "hasCurveTo": true,
        "point": "{0.5, 0}"
      },
      {
        "_class": "curvePoint",
        "cornerRadius": 0,
        "curveFrom": "{1, 0.34375}",
        "curveMode": 3,
        "curveTo": "{1, 0.111328125}",
        "hasCurveFrom": true,
        "hasCurveTo": true,
        "point": "{1, 0.25}"
      },
      {
        "_class": "curvePoint",
        "cornerRadius": 0,
        "curveFrom": "{0.7578125, 0.525390625}",
        "curveMode": 4,
        "curveTo": "{0.89453125, 0.4296875}",
        "hasCurveFrom": true,
        "hasCurveTo": true,
        "point": "{0.7265625, 0.47265625}"
      },
      {
        "_class": "curvePoint",
        "cornerRadius": 0,
        "curveFrom": "{1, 0.9375}",
        "curveMode": 4,
        "curveTo": "{1, 0.91015625}",
        "hasCurveFrom": false,
        "hasCurveTo": true,
        "point": "{1, 0.9375}"
      }
    ]
  },
  "pointRadiusBehaviour": 0,
  "points": [
    {
      "_class": "curvePoint",
      "cornerRadius": 0,
      "curveFrom": "{1, 0.970703125}",
      "curveMode": 4,
      "curveTo": "{1, 0.9375}",
      "hasCurveFrom": true,
      "hasCurveTo": false,
      "point": "{1, 0.9375}"
    },
    {
      "_class": "curvePoint",
      "cornerRadius": 0,
      "curveFrom": "{0.875, 1}",
      "curveMode": 4,
      "curveTo": "{0.94140625, 1}",
      "hasCurveFrom": false,
      "hasCurveTo": true,
      "point": "{0.875, 1}"
    },
    {
      "_class": "curvePoint",
      "cornerRadius": 0,
      "curveFrom": "{0.05859375, 1}",
      "curveMode": 4,
      "curveTo": "{0.125, 1}",
      "hasCurveFrom": true,
      "hasCurveTo": false,
      "point": "{0.125, 1}"
    },
    {
      "_class": "curvePoint",
      "cornerRadius": 0,
      "curveFrom": "{0, 0.91015625}",
      "curveMode": 2,
      "curveTo": "{0, 0.970703125}",
      "hasCurveFrom": true,
      "hasCurveTo": true,
      "point": "{0, 0.9375}"
    },
    {
      "_class": "curvePoint",
      "cornerRadius": 0,
      "curveFrom": "{0.109375, 0.4296875}",
      "curveMode": 4,
      "curveTo": "{0.2421875, 0.525390625}",
      "hasCurveFrom": true,
      "hasCurveTo": true,
      "point": "{0.2734375, 0.47265625}"
    },
    {
      "_class": "curvePoint",
      "cornerRadius": 0,
      "curveFrom": "{0, 0.111328125}",
      "curveMode": 3,
      "curveTo": "{0, 0.34375}",
      "hasCurveFrom": true,
      "hasCurveTo": true,
      "point": "{0, 0.25}"
    },
    {
      "_class": "curvePoint",
      "cornerRadius": 0,
      "curveFrom": "{0.77734375, 0}",
      "curveMode": 2,
      "curveTo": "{0.22265625, 0}",
      "hasCurveFrom": true,
      "hasCurveTo": true,
      "point": "{0.5, 0}"
    },
    {
      "_class": "curvePoint",
      "cornerRadius": 0,
      "curveFrom": "{1, 0.34375}",
      "curveMode": 3,
      "curveTo": "{1, 0.111328125}",
      "hasCurveFrom": true,
      "hasCurveTo": true,
      "point": "{1, 0.25}"
    },
    {
      "_class": "curvePoint",
      "cornerRadius": 0,
      "curveFrom": "{0.7578125, 0.525390625}",
      "curveMode": 4,
      "curveTo": "{0.89453125, 0.4296875}",
      "hasCurveFrom": true,
      "hasCurveTo": true,
      "point": "{0.7265625, 0.47265625}"
    },
    {
      "_class": "curvePoint",
      "cornerRadius": 0,
      "curveFrom": "{1, 0.9375}",
      "curveMode": 4,
      "curveTo": "{1, 0.91015625}",
      "hasCurveFrom": false,
      "hasCurveTo": true,
      "point": "{1, 0.9375}"
    }
  ],
  "resizingConstraint": 63,
  "resizingType": 0,
  "rotation": 0,
  "shouldBreakMaskChain": false
}