{
  "_class": "shapeGroup",
  "clippingMaskMode": 0,
  "do_objectID": "DA7212A2-9AFE-4D9C-B301-321BC834B600",
  "exportOptions": {
    "_class": "exportOptions",
    "exportFormats": [
    ],
    "includedLayerIds": [
    ],
    "layerOptions": 0,
    "shouldTrim": false
  },
  "frame": {
    "_class": "rect",
    "constrainProportions": false,
    "do_objectID": "1ED1E173-5C10-4038-86B9-AE0F41876132",
    "height": 18.94736842105263,
    "width": 19.88461538461537,
    "x": 79,
    "y": 0.2783203125
  },
  "hasClickThrough": false,
  "hasClippingMask": false,
  "isFlippedHorizontal": false,
  "isFlippedVertical": false,
  "isLocked": false,
  "isVisible": true,
  "layerListExpandedType": 0,
  "layers": [
    {
      "class": "shapePath",
      "id": "4ECDBD2C-C634-42CA-9F85-91438872566D"
    }
  ],
  "name": "user ico",
  "nameIsFixed": true,
  "resizingConstraint": 63,
  "resizingType": 0,
  "rotation": 0,
  "shouldBreakMaskChain": false,
  "style": {
    "_class": "style",
    "borders": [
      {
        "_class": "border",
        "color": {
          "_class": "color",
          "alpha": 1,
          "blue": 0.592,
          "green": 0.592,
          "red": 0.592
        },
        "fillType": 0,
        "isEnabled": false,
        "position": 1,
        "thickness": 1
      }
    ],
    "do_objectID": "0F636707-A3CF-48C3-9307-BD1682E62005",
    "endDecorationType": 0,
    "fills": [
      {
        "_class": "fill",
        "color": {
          "_class": "color",
          "alpha": 1,
          "blue": 0.8361766581632653,
          "green": 0.8266433274290891,
          "red": 0.8178984909985537
        },
        "fillType": 0,
        "isEnabled": true,
        "noiseIndex": 0,
        "noiseIntensity": 0,
        "patternFillType": 0,
        "patternTileScale": 1
      }
    ],
    "miterLimit": 10,
    "sharedObjectID": "4226A5EE-0022-4CCE-95DA-BC7A1D8FFDB6",
    "startDecorationType": 0
  },
  "windingRule": 1
}